{
  "asyncpg": {
    "summary": "An asyncio PostgreSQL driver",
    "potential_require": [
      "typing-extensions"
    ],
    "version_list": [
      {
        "version": "0.26.0",
        "upload_time": "2022-07-07T19:21:14",
        "python_require": [
          "cp311",
          "cp37",
          "cp310",
          "cp39",
          "cp36",
          "cp38"
        ],
        "requirement": [
          {
            "skip_list": [],
            "package_name": "typing-extensions",
            "start_node": "START",
            "end_node": "3.7.4.3",
            "is_skip_start": false,
            "is_skip_end": false,
            "python_list": [
              "cp311",
              "cp37",
              "cp310",
              "cp36",
              "cp38",
              "cp39"
            ]
          }
        ],
        "combine": false
      },
      {
        "version": "0.25.0",
        "upload_time": "2021-11-16T22:58:03",
        "python_require": [
          "cp311",
          "cp37",
          "cp310",
          "cp39",
          "cp36",
          "cp38"
        ],
        "requirement": [
          {
            "skip_list": [],
            "package_name": "typing-extensions",
            "start_node": "START",
            "end_node": "3.7.4.3",
            "is_skip_start": false,
            "is_skip_end": false,
            "python_list": [
              "cp311",
              "cp37",
              "cp310",
              "cp36",
              "cp38",
              "cp39"
            ]
          }
        ],
        "combine": true
      },
      {
        "version": "0.24.0",
        "upload_time": "2021-08-10T05:27:23",
        "python_require": [
          "cp311",
          "cp37",
          "cp310",
          "cp36",
          "cp38",
          "cp39"
        ],
        "requirement": [
          {
            "skip_list": [],
            "package_name": "typing-extensions",
            "start_node": "START",
            "end_node": "3.7.4.3",
            "is_skip_start": false,
            "is_skip_end": false,
            "python_list": [
              "cp311",
              "cp37",
              "cp310",
              "cp39",
              "cp36",
              "cp38"
            ]
          }
        ],
        "combine": false
      },
      {
        "version": "0.23.0",
        "upload_time": "2021-05-17T19:02:32",
        "python_require": [
          "cp311",
          "cp37",
          "cp310",
          "cp36",
          "cp38",
          "cp35",
          "cp39"
        ],
        "requirement": [
          {
            "skip_list": [],
            "package_name": "typing-extensions",
            "start_node": "START",
            "end_node": "3.7.4.3",
            "is_skip_start": false,
            "is_skip_end": false,
            "python_list": [
              "cp311",
              "cp37",
              "cp310",
              "cp39",
              "cp36",
              "cp35",
              "cp38"
            ]
          }
        ],
        "combine": false
      },
      {
        "version": "0.22.0",
        "upload_time": "2021-02-10T05:48:50",
        "python_require": [
          "cp311",
          "cp37",
          "cp310",
          "cp36",
          "cp38",
          "cp35",
          "cp39"
        ],
        "requirement": [
          {
            "skip_list": [],
            "package_name": "typing-extensions",
            "start_node": "START",
            "end_node": "3.7.4.3",
            "is_skip_start": false,
            "is_skip_end": false,
            "python_list": [
              "cp311",
              "cp37",
              "cp310",
              "cp39",
              "cp36",
              "cp35",
              "cp38"
            ]
          }
        ],
        "combine": true
      },
      {
        "version": "0.21.0",
        "upload_time": "2020-08-09T22:27:42",
        "python_require": [
          "cp311",
          "cp37",
          "cp310",
          "cp36",
          "cp38",
          "cp35",
          "cp39"
        ],
        "requirement": [],
        "combine": false
      },
      {
        "version": "0.20.1",
        "upload_time": "2020-01-13T00:29:00",
        "python_require": [
          "cp311",
          "cp37",
          "cp310",
          "cp36",
          "cp38",
          "cp35",
          "cp39"
        ],
        "requirement": [],
        "combine": true
      },
      {
        "version": "0.20.0",
        "upload_time": "2019-11-20T22:45:15",
        "python_require": [
          "cp311",
          "cp37",
          "cp310",
          "cp36",
          "cp38",
          "cp35",
          "cp39"
        ],
        "requirement": [],
        "combine": true
      },
      {
        "version": "0.19.0",
        "upload_time": "2019-10-09T19:03:39",
        "python_require": [
          "cp311",
          "cp37",
          "cp310",
          "cp39",
          "cp36",
          "cp35",
          "cp38"
        ],
        "requirement": [],
        "combine": false
      },
      {
        "version": "0.18.3",
        "upload_time": "2019-01-02T17:33:25",
        "python_require": [
          "cp311",
          "cp37",
          "cp310",
          "cp39",
          "cp36",
          "cp35",
          "cp38"
        ],
        "requirement": [],
        "combine": true
      },
      {
        "version": "0.18.2",
        "upload_time": "2018-11-10T19:13:57",
        "python_require": [
          "cp311",
          "cp37",
          "cp310",
          "cp39",
          "cp36",
          "cp35",
          "cp38"
        ],
        "requirement": [],
        "combine": true
      },
      {
        "version": "0.18.1",
        "upload_time": "2018-10-31T13:54:53",
        "python_require": [
          "cp311",
          "cp37",
          "cp310",
          "cp39",
          "cp36",
          "cp35",
          "cp38"
        ],
        "requirement": [],
        "combine": true
      },
      {
        "version": "0.18.0",
        "upload_time": "2018-10-30T19:55:05",
        "python_require": [
          "cp311",
          "cp37",
          "cp310",
          "cp39",
          "cp36",
          "cp35",
          "cp38"
        ],
        "requirement": [],
        "combine": true
      },
      {
        "version": "0.17.0",
        "upload_time": "2018-07-10T21:51:56",
        "python_require": [
          "cp311",
          "cp37",
          "cp310",
          "cp39",
          "cp36",
          "cp35",
          "cp38"
        ],
        "requirement": [],
        "combine": true
      },
      {
        "version": "0.16.0",
        "upload_time": "2018-06-06T00:53:12",
        "python_require": [
          "cp35",
          "cp36"
        ],
        "requirement": [],
        "combine": false
      },
      {
        "version": "0.15.0",
        "upload_time": "2018-02-15T17:44:52",
        "python_require": [
          "cp35",
          "cp36"
        ],
        "requirement": [],
        "combine": true
      },
      {
        "version": "0.14.0",
        "upload_time": "2017-12-29T18:06:23",
        "python_require": [
          "cp35",
          "cp36"
        ],
        "requirement": [],
        "combine": true
      },
      {
        "version": "0.13.0",
        "upload_time": "2017-10-20T14:58:57",
        "python_require": [
          "cp35",
          "cp36"
        ],
        "requirement": [],
        "combine": true
      },
      {
        "version": "0.12.0",
        "upload_time": "2017-07-07T18:41:00",
        "python_require": [
          "cp35",
          "cp36"
        ],
        "requirement": [],
        "combine": true
      },
      {
        "version": "0.11.0",
        "upload_time": "2017-05-11T22:39:48",
        "python_require": [
          "cp35",
          "cp36"
        ],
        "requirement": [],
        "combine": true
      },
      {
        "version": "0.10.1",
        "upload_time": "2017-04-06T22:27:06",
        "python_require": [
          "cp35",
          "cp36"
        ],
        "requirement": [],
        "combine": true
      },
      {
        "version": "0.10.0",
        "upload_time": "2017-04-04T20:12:54",
        "python_require": [
          "cp35",
          "cp36"
        ],
        "requirement": [],
        "combine": true
      },
      {
        "version": "0.9.0",
        "upload_time": "2017-03-02T13:31:14",
        "python_require": [
          "cp35",
          "cp36"
        ],
        "requirement": [],
        "combine": true
      },
      {
        "version": "0.9.0.dev1",
        "upload_time": "2017-03-02T13:31:41",
        "python_require": [
          "cp35",
          "cp36"
        ],
        "requirement": [],
        "combine": true
      },
      {
        "version": "0.8.4",
        "upload_time": "2017-01-06T00:31:07",
        "python_require": [
          "cp35",
          "cp36"
        ],
        "requirement": [],
        "combine": true
      },
      {
        "version": "0.8.3",
        "upload_time": "2017-01-04T21:28:13",
        "python_require": [
          "cp35",
          "cp36"
        ],
        "requirement": [],
        "combine": true
      },
      {
        "version": "0.8.2",
        "upload_time": "2017-01-02T16:11:09",
        "python_require": [
          "cp35",
          "cp36"
        ],
        "requirement": [],
        "combine": true
      },
      {
        "version": "0.8.1",
        "upload_time": "2016-12-22T17:33:02",
        "python_require": [
          "cp35"
        ],
        "requirement": [],
        "combine": false
      },
      {
        "version": "0.8.0",
        "upload_time": "2016-12-22T16:23:59",
        "python_require": [
          "cp35"
        ],
        "requirement": [],
        "combine": true
      },
      {
        "version": "0.7.0",
        "upload_time": "2016-11-17T14:27:05",
        "python_require": [
          "cp35"
        ],
        "requirement": [],
        "combine": true
      },
      {
        "version": "0.6.3",
        "upload_time": "2016-10-21T22:35:12",
        "python_require": [
          "cp35"
        ],
        "requirement": [],
        "combine": true
      },
      {
        "version": "0.6.2",
        "upload_time": "2016-10-20T17:57:44",
        "python_require": [
          "cp35"
        ],
        "requirement": [],
        "combine": true
      },
      {
        "version": "0.6.1",
        "upload_time": "2016-10-20T17:47:07",
        "python_require": [
          "cp35"
        ],
        "requirement": [],
        "combine": true
      },
      {
        "version": "0.5.4",
        "upload_time": "2016-09-14T17:36:42",
        "python_require": [
          "cp35"
        ],
        "requirement": [],
        "combine": true
      },
      {
        "version": "0.5.3",
        "upload_time": "2016-08-05T16:07:49",
        "python_require": [
          "cp35"
        ],
        "requirement": [],
        "combine": true
      },
      {
        "version": "0.5.2",
        "upload_time": "2016-07-28T23:09:26",
        "python_require": [
          "cp35"
        ],
        "requirement": [],
        "combine": true
      },
      {
        "version": "0.5.1",
        "upload_time": "2016-07-19T21:23:35",
        "python_require": [
          "cp33",
          "cp311",
          "cp31",
          "cp36",
          "cp27",
          "cp34",
          "cp35",
          "cp37",
          "cp32",
          "cp38",
          "cp39",
          "cp310",
          "cp30"
        ],
        "requirement": [],
        "combine": false
      },
      {
        "version": "0.5.0",
        "upload_time": "2016-07-18T23:03:47",
        "python_require": [
          "cp33",
          "cp311",
          "cp31",
          "cp36",
          "cp27",
          "cp34",
          "cp35",
          "cp37",
          "cp32",
          "cp38",
          "cp39",
          "cp310",
          "cp30"
        ],
        "requirement": [],
        "combine": true
      }
    ],
    "build_version": "0.0.3"
  }
}