{
  "ml-collections": {
    "summary": "ML Collections is a library of Python collections designed for ML usecases.",
    "potential_require": [
      "typing",
      "contextlib2",
      "six",
      "PyYAML",
      "absl-py"
    ],
    "version_list": [
      {
        "version": "0.1.1",
        "upload_time": "2022-01-27T12:39:20",
        "python_require": [
          "cp36",
          "cp30",
          "cp34",
          "cp31",
          "cp38",
          "cp39",
          "cp311",
          "cp32",
          "cp37",
          "cp27",
          "cp33",
          "cp310",
          "cp35"
        ],
        "requirement": [],
        "combine": false
      },
      {
        "version": "0.1.0",
        "upload_time": "2020-08-24T04:43:42",
        "python_require": [
          "cp36",
          "cp30",
          "cp34",
          "cp31",
          "cp38",
          "cp39",
          "cp311",
          "cp32",
          "cp37",
          "cp27",
          "cp33",
          "cp310",
          "cp35"
        ],
        "requirement": [
          {
            "skip_list": [],
            "package_name": "typing",
            "start_node": "START",
            "end_node": "END",
            "is_skip_start": false,
            "is_skip_end": true,
            "python_list": [
              "cp36",
              "cp34",
              "cp38",
              "cp31",
              "cp39",
              "cp311",
              "cp32",
              "cp37",
              "cp27",
              "cp30",
              "cp310",
              "cp33",
              "cp35"
            ]
          },
          {
            "skip_list": [],
            "package_name": "contextlib2",
            "start_node": "START",
            "end_node": "END",
            "is_skip_start": false,
            "is_skip_end": true,
            "python_list": [
              "cp36",
              "cp34",
              "cp38",
              "cp31",
              "cp39",
              "cp311",
              "cp32",
              "cp37",
              "cp27",
              "cp30",
              "cp310",
              "cp33",
              "cp35"
            ]
          },
          {
            "skip_list": [],
            "package_name": "six",
            "start_node": "START",
            "end_node": "END",
            "is_skip_start": false,
            "is_skip_end": true,
            "python_list": [
              "cp36",
              "cp34",
              "cp38",
              "cp31",
              "cp39",
              "cp311",
              "cp32",
              "cp37",
              "cp27",
              "cp30",
              "cp310",
              "cp33",
              "cp35"
            ]
          },
          {
            "skip_list": [],
            "package_name": "PyYAML",
            "start_node": "START",
            "end_node": "END",
            "is_skip_start": false,
            "is_skip_end": true,
            "python_list": [
              "cp36",
              "cp34",
              "cp38",
              "cp31",
              "cp39",
              "cp311",
              "cp32",
              "cp37",
              "cp27",
              "cp30",
              "cp310",
              "cp33",
              "cp35"
            ]
          },
          {
            "skip_list": [],
            "package_name": "absl-py",
            "start_node": "START",
            "end_node": "END",
            "is_skip_start": false,
            "is_skip_end": true,
            "python_list": [
              "cp36",
              "cp34",
              "cp38",
              "cp31",
              "cp39",
              "cp311",
              "cp32",
              "cp37",
              "cp27",
              "cp30",
              "cp310",
              "cp33",
              "cp35"
            ]
          }
        ],
        "combine": false
      }
    ],
    "build_version": "0.0.3"
  }
}