{"sphinx-inline-tabs": {"summary": "Add inline tabbed content to your Sphinx documentation.", "potential_require": ["sphinx", "myst-parser", "furo", "pytest", "pytest-cov", "pytest-xdist"], "version_list": [{"version": "2022.1.2b11", "upload_time": "2022-01-02T17:36:03", "python_require": ["cp38", "cp311", "cp310", "cp39"], "requirement": [{"skip_list": [], "package_name": "sphinx", "start_node": "START", "end_node": "3", "is_skip_start": false, "is_skip_end": false, "python_list": ["cp39", "cp38", "cp310", "cp311"]}, {"skip_list": [], "package_name": "myst-parser", "start_node": "START", "end_node": "END", "is_skip_start": false, "is_skip_end": true, "python_list": ["cp39", "cp38", "cp310", "cp311"]}, {"skip_list": [], "package_name": "furo", "start_node": "START", "end_node": "END", "is_skip_start": false, "is_skip_end": true, "python_list": ["cp39", "cp38", "cp310", "cp311"]}, {"skip_list": [], "package_name": "pytest", "start_node": "START", "end_node": "END", "is_skip_start": false, "is_skip_end": true, "python_list": ["cp39", "cp38", "cp310", "cp311"]}, {"skip_list": [], "package_name": "pytest-cov", "start_node": "START", "end_node": "END", "is_skip_start": false, "is_skip_end": true, "python_list": ["cp39", "cp38", "cp310", "cp311"]}, {"skip_list": [], "package_name": "pytest-xdist", "start_node": "START", "end_node": "END", "is_skip_start": false, "is_skip_end": true, "python_list": ["cp39", "cp38", "cp310", "cp311"]}], "combine": false}, {"version": "2021.8.17b10", "upload_time": "2021-08-17T08:23:37", "python_require": ["cp38", "cp311", "cp310", "cp39"], "requirement": [{"skip_list": [], "package_name": "sphinx", "start_node": "START", "end_node": "3", "is_skip_start": false, "is_skip_end": false, "python_list": ["cp39", "cp38", "cp310", "cp311"]}, {"skip_list": [], "package_name": "myst-parser", "start_node": "START", "end_node": "END", "is_skip_start": false, "is_skip_end": true, "python_list": ["cp39", "cp38", "cp310", "cp311"]}, {"skip_list": [], "package_name": "furo", "start_node": "START", "end_node": "END", "is_skip_start": false, "is_skip_end": true, "python_list": ["cp39", "cp38", "cp310", "cp311"]}, {"skip_list": [], "package_name": "pytest", "start_node": "START", "end_node": "END", "is_skip_start": false, "is_skip_end": true, "python_list": ["cp39", "cp38", "cp310", "cp311"]}, {"skip_list": [], "package_name": "pytest-cov", "start_node": "START", "end_node": "END", "is_skip_start": false, "is_skip_end": true, "python_list": ["cp39", "cp38", "cp310", "cp311"]}, {"skip_list": [], "package_name": "pytest-xdist", "start_node": "START", "end_node": "END", "is_skip_start": false, "is_skip_end": true, "python_list": ["cp39", "cp38", "cp310", "cp311"]}], "combine": true}, {"version": "2021.4.11b9", "upload_time": "2021-04-11T19:02:23", "python_require": ["cp38", "cp311", "cp310", "cp39"], "requirement": [{"skip_list": [], "package_name": "sphinx", "start_node": "START", "end_node": "3", "is_skip_start": false, "is_skip_end": false, "python_list": ["cp39", "cp38", "cp310", "cp311"]}, {"skip_list": [], "package_name": "myst-parser", "start_node": "START", "end_node": "END", "is_skip_start": false, "is_skip_end": true, "python_list": ["cp39", "cp38", "cp310", "cp311"]}, {"skip_list": [], "package_name": "furo", "start_node": "START", "end_node": "END", "is_skip_start": false, "is_skip_end": true, "python_list": ["cp39", "cp38", "cp310", "cp311"]}, {"skip_list": [], "package_name": "pytest", "start_node": "START", "end_node": "END", "is_skip_start": false, "is_skip_end": true, "python_list": ["cp39", "cp38", "cp310", "cp311"]}, {"skip_list": [], "package_name": "pytest-cov", "start_node": "START", "end_node": "END", "is_skip_start": false, "is_skip_end": true, "python_list": ["cp39", "cp38", "cp310", "cp311"]}, {"skip_list": [], "package_name": "pytest-xdist", "start_node": "START", "end_node": "END", "is_skip_start": false, "is_skip_end": true, "python_list": ["cp39", "cp38", "cp310", "cp311"]}], "combine": true}, {"version": "2021.4.11b8", "upload_time": "2021-04-11T11:07:04", "python_require": ["cp37", "cp39", "cp311", "cp38", "cp310", "cp36"], "requirement": [{"skip_list": [], "package_name": "sphinx", "start_node": "START", "end_node": "3", "is_skip_start": false, "is_skip_end": false, "python_list": ["cp37", "cp39", "cp311", "cp38", "cp310", "cp36"]}, {"skip_list": [], "package_name": "myst-parser", "start_node": "START", "end_node": "END", "is_skip_start": false, "is_skip_end": true, "python_list": ["cp37", "cp39", "cp311", "cp38", "cp310", "cp36"]}, {"skip_list": [], "package_name": "furo", "start_node": "START", "end_node": "END", "is_skip_start": false, "is_skip_end": true, "python_list": ["cp37", "cp39", "cp311", "cp38", "cp310", "cp36"]}, {"skip_list": [], "package_name": "pytest", "start_node": "START", "end_node": "END", "is_skip_start": false, "is_skip_end": true, "python_list": ["cp37", "cp39", "cp311", "cp38", "cp310", "cp36"]}, {"skip_list": [], "package_name": "pytest-cov", "start_node": "START", "end_node": "END", "is_skip_start": false, "is_skip_end": true, "python_list": ["cp37", "cp39", "cp311", "cp38", "cp310", "cp36"]}, {"skip_list": [], "package_name": "pytest-xdist", "start_node": "START", "end_node": "END", "is_skip_start": false, "is_skip_end": true, "python_list": ["cp37", "cp39", "cp311", "cp38", "cp310", "cp36"]}], "combine": false}, {"version": "2021.3.28b7", "upload_time": "2021-03-28T07:40:40", "python_require": ["cp37", "cp39", "cp311", "cp38", "cp310", "cp36"], "requirement": [{"skip_list": [], "package_name": "sphinx", "start_node": "START", "end_node": "3", "is_skip_start": false, "is_skip_end": false, "python_list": ["cp37", "cp39", "cp311", "cp38", "cp310", "cp36"]}, {"skip_list": [], "package_name": "myst-parser", "start_node": "START", "end_node": "END", "is_skip_start": false, "is_skip_end": true, "python_list": ["cp37", "cp39", "cp311", "cp38", "cp310", "cp36"]}, {"skip_list": [], "package_name": "furo", "start_node": "START", "end_node": "END", "is_skip_start": false, "is_skip_end": true, "python_list": ["cp37", "cp39", "cp311", "cp38", "cp310", "cp36"]}, {"skip_list": [], "package_name": "pytest", "start_node": "START", "end_node": "END", "is_skip_start": false, "is_skip_end": true, "python_list": ["cp37", "cp39", "cp311", "cp38", "cp310", "cp36"]}, {"skip_list": [], "package_name": "pytest-cov", "start_node": "START", "end_node": "END", "is_skip_start": false, "is_skip_end": true, "python_list": ["cp37", "cp39", "cp311", "cp38", "cp310", "cp36"]}, {"skip_list": [], "package_name": "pytest-xdist", "start_node": "START", "end_node": "END", "is_skip_start": false, "is_skip_end": true, "python_list": ["cp37", "cp39", "cp311", "cp38", "cp310", "cp36"]}], "combine": true}, {"version": "2021.3.28b6", "upload_time": "2021-03-28T07:37:37", "python_require": ["cp37", "cp39", "cp311", "cp38", "cp310", "cp36"], "requirement": [{"skip_list": [], "package_name": "sphinx", "start_node": "START", "end_node": "3", "is_skip_start": false, "is_skip_end": false, "python_list": ["cp37", "cp39", "cp311", "cp38", "cp310", "cp36"]}, {"skip_list": [], "package_name": "myst-parser", "start_node": "START", "end_node": "END", "is_skip_start": false, "is_skip_end": true, "python_list": ["cp37", "cp39", "cp311", "cp38", "cp310", "cp36"]}, {"skip_list": [], "package_name": "furo", "start_node": "START", "end_node": "END", "is_skip_start": false, "is_skip_end": true, "python_list": ["cp37", "cp39", "cp311", "cp38", "cp310", "cp36"]}, {"skip_list": [], "package_name": "pytest", "start_node": "START", "end_node": "END", "is_skip_start": false, "is_skip_end": true, "python_list": ["cp37", "cp39", "cp311", "cp38", "cp310", "cp36"]}, {"skip_list": [], "package_name": "pytest-cov", "start_node": "START", "end_node": "END", "is_skip_start": false, "is_skip_end": true, "python_list": ["cp37", "cp39", "cp311", "cp38", "cp310", "cp36"]}, {"skip_list": [], "package_name": "pytest-xdist", "start_node": "START", "end_node": "END", "is_skip_start": false, "is_skip_end": true, "python_list": ["cp37", "cp39", "cp311", "cp38", "cp310", "cp36"]}], "combine": true}, {"version": "2021.3.19b5", "upload_time": "2021-03-19T19:05:32", "python_require": ["cp37", "cp39", "cp311", "cp35", "cp38", "cp310", "cp36"], "requirement": [{"skip_list": [], "package_name": "sphinx", "start_node": "START", "end_node": "3", "is_skip_start": false, "is_skip_end": false, "python_list": ["cp37", "cp39", "cp311", "cp36", "cp310", "cp35", "cp38"]}, {"skip_list": [], "package_name": "myst-parser", "start_node": "START", "end_node": "END", "is_skip_start": false, "is_skip_end": true, "python_list": ["cp37", "cp39", "cp311", "cp36", "cp310", "cp35", "cp38"]}, {"skip_list": [], "package_name": "furo", "start_node": "START", "end_node": "END", "is_skip_start": false, "is_skip_end": true, "python_list": ["cp37", "cp39", "cp311", "cp36", "cp310", "cp35", "cp38"]}, {"skip_list": [], "package_name": "pytest", "start_node": "START", "end_node": "END", "is_skip_start": false, "is_skip_end": true, "python_list": ["cp37", "cp39", "cp311", "cp36", "cp310", "cp35", "cp38"]}, {"skip_list": [], "package_name": "pytest-cov", "start_node": "START", "end_node": "END", "is_skip_start": false, "is_skip_end": true, "python_list": ["cp37", "cp39", "cp311", "cp36", "cp310", "cp35", "cp38"]}, {"skip_list": [], "package_name": "pytest-xdist", "start_node": "START", "end_node": "END", "is_skip_start": false, "is_skip_end": true, "python_list": ["cp37", "cp39", "cp311", "cp36", "cp310", "cp35", "cp38"]}], "combine": false}, {"version": "2020.10.19b4", "upload_time": "2020-10-19T18:24:16", "python_require": ["cp37", "cp39", "cp311", "cp35", "cp38", "cp310", "cp36"], "requirement": [{"skip_list": [], "package_name": "sphinx", "start_node": "START", "end_node": "3", "is_skip_start": false, "is_skip_end": false, "python_list": ["cp37", "cp39", "cp311", "cp36", "cp310", "cp35", "cp38"]}, {"skip_list": [], "package_name": "myst-parser", "start_node": "START", "end_node": "END", "is_skip_start": false, "is_skip_end": true, "python_list": ["cp37", "cp39", "cp311", "cp36", "cp310", "cp35", "cp38"]}, {"skip_list": [], "package_name": "furo", "start_node": "START", "end_node": "END", "is_skip_start": false, "is_skip_end": true, "python_list": ["cp37", "cp39", "cp311", "cp36", "cp310", "cp35", "cp38"]}, {"skip_list": [], "package_name": "pytest", "start_node": "START", "end_node": "END", "is_skip_start": false, "is_skip_end": true, "python_list": ["cp37", "cp39", "cp311", "cp36", "cp310", "cp35", "cp38"]}, {"skip_list": [], "package_name": "pytest-cov", "start_node": "START", "end_node": "END", "is_skip_start": false, "is_skip_end": true, "python_list": ["cp37", "cp39", "cp311", "cp36", "cp310", "cp35", "cp38"]}, {"skip_list": [], "package_name": "pytest-xdist", "start_node": "START", "end_node": "END", "is_skip_start": false, "is_skip_end": true, "python_list": ["cp37", "cp39", "cp311", "cp36", "cp310", "cp35", "cp38"]}], "combine": true}, {"version": "2020.10.19b3", "upload_time": "2020-10-19T13:24:24", "python_require": ["cp37", "cp39", "cp311", "cp35", "cp38", "cp310", "cp36"], "requirement": [{"skip_list": [], "package_name": "sphinx", "start_node": "START", "end_node": "3", "is_skip_start": false, "is_skip_end": false, "python_list": ["cp37", "cp39", "cp311", "cp36", "cp310", "cp35", "cp38"]}, {"skip_list": [], "package_name": "myst-parser", "start_node": "START", "end_node": "END", "is_skip_start": false, "is_skip_end": true, "python_list": ["cp37", "cp39", "cp311", "cp36", "cp310", "cp35", "cp38"]}, {"skip_list": [], "package_name": "furo", "start_node": "START", "end_node": "END", "is_skip_start": false, "is_skip_end": true, "python_list": ["cp37", "cp39", "cp311", "cp36", "cp310", "cp35", "cp38"]}, {"skip_list": [], "package_name": "pytest", "start_node": "START", "end_node": "END", "is_skip_start": false, "is_skip_end": true, "python_list": ["cp37", "cp39", "cp311", "cp36", "cp310", "cp35", "cp38"]}, {"skip_list": [], "package_name": "pytest-cov", "start_node": "START", "end_node": "END", "is_skip_start": false, "is_skip_end": true, "python_list": ["cp37", "cp39", "cp311", "cp36", "cp310", "cp35", "cp38"]}, {"skip_list": [], "package_name": "pytest-xdist", "start_node": "START", "end_node": "END", "is_skip_start": false, "is_skip_end": true, "python_list": ["cp37", "cp39", "cp311", "cp36", "cp310", "cp35", "cp38"]}], "combine": true}, {"version": "2020.10.16b2", "upload_time": "2020-10-16T13:12:26", "python_require": ["cp37", "cp39", "cp311", "cp35", "cp38", "cp310", "cp36"], "requirement": [{"skip_list": [], "package_name": "sphinx", "start_node": "START", "end_node": "3", "is_skip_start": false, "is_skip_end": false, "python_list": ["cp37", "cp39", "cp311", "cp36", "cp310", "cp35", "cp38"]}, {"skip_list": [], "package_name": "myst-parser", "start_node": "START", "end_node": "END", "is_skip_start": false, "is_skip_end": true, "python_list": ["cp37", "cp39", "cp311", "cp36", "cp310", "cp35", "cp38"]}, {"skip_list": [], "package_name": "furo", "start_node": "START", "end_node": "END", "is_skip_start": false, "is_skip_end": true, "python_list": ["cp37", "cp39", "cp311", "cp36", "cp310", "cp35", "cp38"]}, {"skip_list": [], "package_name": "pytest", "start_node": "START", "end_node": "END", "is_skip_start": false, "is_skip_end": true, "python_list": ["cp37", "cp39", "cp311", "cp36", "cp310", "cp35", "cp38"]}, {"skip_list": [], "package_name": "pytest-cov", "start_node": "START", "end_node": "END", "is_skip_start": false, "is_skip_end": true, "python_list": ["cp37", "cp39", "cp311", "cp36", "cp310", "cp35", "cp38"]}, {"skip_list": [], "package_name": "pytest-xdist", "start_node": "START", "end_node": "END", "is_skip_start": false, "is_skip_end": true, "python_list": ["cp37", "cp39", "cp311", "cp36", "cp310", "cp35", "cp38"]}], "combine": true}, {"version": "2020.10.15b1", "upload_time": "2020-10-14T18:40:00", "python_require": ["cp37", "cp39", "cp311", "cp35", "cp38", "cp310", "cp36"], "requirement": [{"skip_list": [], "package_name": "sphinx", "start_node": "START", "end_node": "3", "is_skip_start": false, "is_skip_end": false, "python_list": ["cp37", "cp39", "cp311", "cp36", "cp310", "cp35", "cp38"]}, {"skip_list": [], "package_name": "myst-parser", "start_node": "START", "end_node": "END", "is_skip_start": false, "is_skip_end": true, "python_list": ["cp37", "cp39", "cp311", "cp36", "cp310", "cp35", "cp38"]}, {"skip_list": [], "package_name": "furo", "start_node": "START", "end_node": "END", "is_skip_start": false, "is_skip_end": true, "python_list": ["cp37", "cp39", "cp311", "cp36", "cp310", "cp35", "cp38"]}, {"skip_list": [], "package_name": "pytest", "start_node": "START", "end_node": "END", "is_skip_start": false, "is_skip_end": true, "python_list": ["cp37", "cp39", "cp311", "cp36", "cp310", "cp35", "cp38"]}, {"skip_list": [], "package_name": "pytest-cov", "start_node": "START", "end_node": "END", "is_skip_start": false, "is_skip_end": true, "python_list": ["cp37", "cp39", "cp311", "cp36", "cp310", "cp35", "cp38"]}, {"skip_list": [], "package_name": "pytest-xdist", "start_node": "START", "end_node": "END", "is_skip_start": false, "is_skip_end": true, "python_list": ["cp37", "cp39", "cp311", "cp36", "cp310", "cp35", "cp38"]}], "combine": true}, {"version": "2020.10.14b0", "upload_time": "2020-10-14T13:45:29", "python_require": ["cp37", "cp39", "cp311", "cp35", "cp38", "cp310", "cp36"], "requirement": [{"skip_list": [], "package_name": "sphinx", "start_node": "START", "end_node": "3", "is_skip_start": false, "is_skip_end": false, "python_list": ["cp37", "cp39", "cp311", "cp36", "cp310", "cp35", "cp38"]}, {"skip_list": [], "package_name": "myst-parser", "start_node": "START", "end_node": "END", "is_skip_start": false, "is_skip_end": true, "python_list": ["cp37", "cp39", "cp311", "cp36", "cp310", "cp35", "cp38"]}, {"skip_list": [], "package_name": "furo", "start_node": "START", "end_node": "END", "is_skip_start": false, "is_skip_end": true, "python_list": ["cp37", "cp39", "cp311", "cp36", "cp310", "cp35", "cp38"]}, {"skip_list": [], "package_name": "pytest", "start_node": "START", "end_node": "END", "is_skip_start": false, "is_skip_end": true, "python_list": ["cp37", "cp39", "cp311", "cp36", "cp310", "cp35", "cp38"]}, {"skip_list": [], "package_name": "pytest-cov", "start_node": "START", "end_node": "END", "is_skip_start": false, "is_skip_end": true, "python_list": ["cp37", "cp39", "cp311", "cp36", "cp310", "cp35", "cp38"]}, {"skip_list": [], "package_name": "pytest-xdist", "start_node": "START", "end_node": "END", "is_skip_start": false, "is_skip_end": true, "python_list": ["cp37", "cp39", "cp311", "cp36", "cp310", "cp35", "cp38"]}], "combine": true}], "build_version": "0.0.3"}}